LICENSE
README.md
setup.py
procpy/__init__.py
procpy.egg-info/PKG-INFO
procpy.egg-info/SOURCES.txt
procpy.egg-info/dependency_links.txt
procpy.egg-info/top_level.txt